factro_client/__init__.py
factro_client/controlling/__init__.py
factro_client/controlling/client.py
factro_client/core/__init__.py
factro_client/core/client.py
factro_client/core/exceptions.py
factro_client/core/helpers/__init__.py
factro_client/core/helpers/base_handler.py
factro_client/core/helpers/company_handler.py
factro_client/core/helpers/contact_handler.py
factro_client/core/helpers/package_handler.py
factro_client/core/helpers/project_handler.py
factro_client/core/helpers/task_handler.py
factro_client/core/helpers/user_handler.py
factro_client/core/helpers/work_record_handler.py
factro_client/effort_estimation/__init__.py
factro_client/effort_estimation/client.py
factro_client-0.11.0a1.dist-info/METADATA
factro_client-0.11.0a1.dist-info/WHEEL
factro_client-0.11.0a1.dist-info/top_level.txt
factro_client-0.11.0a1.dist-info/RECORD
