Metadata-Version: 2.1
Name: factro-client
Version: 0.11.0a1
Summary: A core api client for project management tool 'factro'.
Home-page: https://github.com/5minds/factro_client
Author: 5Minds IT-Solutions GmbH & Co. KG
Author-email: developers@5minds.de
Keywords: client factro 5minds processcube
Classifier: Programming Language :: Python :: 3
Classifier: License :: OSI Approved :: MIT License
Classifier: Operating System :: OS Independent
Requires-Dist: cachetools
Requires-Dist: dataclasses-json
Requires-Dist: requests
Requires-Dist: typing-extensions
Requires-Dist: python-dotenv
Requires-Dist: pandas
Requires-Dist: tzlocal (==5.0.1)
